{
  "project_info": {
    "project_number": "311425347794",
    "firebase_url": "https://ingetracespa.firebaseio.com",
    "project_id": "ingetracespa",
    "storage_bucket": "ingetracespa.appspot.com"
  },
  "client": [
    {
      "client_info": {
        "mobilesdk_app_id": "1:311425347794:android:6743f6380cfd1ed6",
        "android_client_info": {
          "package_name": "com.phonegap.ingetrace"
        }
      },
      "oauth_client": [
        {
          "client_id": "311425347794-bpjs8vcrb025p8lb3oh3jbdp0e97u3bj.apps.googleusercontent.com",
          "client_type": 3
        },
        {
          "client_id": "311425347794-bpjs8vcrb025p8lb3oh3jbdp0e97u3bj.apps.googleusercontent.com",
          "client_type": 3
        }
      ],
      "api_key": [
        {
          "current_key": "AIzaSyBqiFBQcnFqWALGtpDdOOwtYHHc2koojW4"
        }
      ],
      "services": {
        "analytics_service": {
          "status": 1
        },
        "appinvite_service": {
          "status": 1,
          "other_platform_oauth_client": []
        },
        "ads_service": {
          "status": 2
        }
      }
    }
  ],
  "configuration_version": "1"
}